{
  "spotId": "vsRFI-BB-UTG",
  "source": "本プロジェクトの自作データ。6max NLH 100bb 公開知見ベースの手動構築値。BB defend vs UTG open 2.5bb。3bet ~6-7%, call ~26%。",
  "notes": "UTGはレンジが最もtightなので、3betはvalue寄りに絞り、ブラフは select の Axs/Kxs/SC のみ。call は wide。",
  "betSizes": {
    "open": "2.5bb",
    "threeBetOop": "12bb (OOP は 4-5x が標準)"
  },
  "longDescription": "UTG のレンジは tight(~16%) でプレミア主体。BB は既に 1bb 投資済みでクロージング、ポットオッズが良くwide defendが正しい。3betはvalueに絞り、ブラフは A5s-A2s と一部 Kxs/SC。",
  "keyPoints": [
    "UTG はレンジが狭いので 3bet value は QQ+/AKs/AKo に絞る",
    "JJ-TT は mostly call。IPの3bet vs UTG とは違い、value 3bet にしすぎない",
    "wheel suited (A5s-A2s) が主なブラフ。Kxs-low や 76s/65s/54s もブラフ候補",
    "ATo/A9o などの dominated offsuit は fold で問題ない",
    "K9s-Q9s-J9s-T9s-98s 等のミドル suited は基本 call"
  ],
  "defaultMistakeLoss": {
    "fold": 0.15,
    "call": 0.10,
    "3bet": 0.10
  },
  "evOverrides": {
    "AA":   { "fold": 5.0, "call": 1.5 },
    "KK":   { "fold": 4.0, "call": 1.2 },
    "QQ":   { "fold": 3.0, "call": 0.8 },
    "AKs":  { "fold": 2.5, "call": 0.5 },
    "AKo":  { "fold": 2.0, "call": 0.4 },
    "JJ":   { "fold": 1.5 },
    "AQs":  { "fold": 1.0 },
    "32o":  { "call": 0.30, "3bet": 0.40 },
    "72o":  { "call": 0.30, "3bet": 0.40 }
  },
  "handNotes": {
    "AA": "ほぼ常に 3bet（value）。slowplay は非推奨",
    "KK": "ほぼ常に 3bet",
    "QQ": "3bet。UTG の AK/AQ から value を取る",
    "JJ": "vs UTG では mostly call（mix 約 60% call / 40% 3bet）",
    "TT": "mostly call。3bet は select",
    "AKs": "3bet value",
    "AKo": "3bet value",
    "AQs": "mix（3bet ~50%、call ~50%）",
    "AJs": "mostly call。境界 3bet",
    "ATs": "call",
    "A5s": "主要ブラフ。3bet ~55% / call ~45% mix",
    "A4s": "ブラフ mix（~40%）",
    "AQo": "mostly call。3bet は ~25%",
    "AJo": "call。3bet は基本しない",
    "ATo": "fold が多い。call は薄い（境界）",
    "KQs": "mix（3bet ~30%、call ~70%）",
    "K5s": "ブラフ候補。3bet ~35%",
    "76s": "call が主。一部 3bet mix（~25%）",
    "65s": "call が主。一部 3bet mix（~25%）",
    "54s": "call。3bet mix（~20%）"
  },
  "strategy": {
    "3bet": [
      "AA",
      "KK",
      "QQ",
      "JJ@0.4",
      "TT@0.15",
      "AKs",
      "AKo",
      "AQs@0.5",
      "AQo@0.25",
      "AJs@0.2",
      "A5s@0.55",
      "A4s@0.4",
      "A3s@0.3",
      "A2s@0.2",
      "KQs@0.3",
      "KQo@0.1",
      "K5s@0.35",
      "K4s@0.3",
      "K3s@0.2",
      "K2s@0.1",
      "76s@0.25",
      "65s@0.25",
      "54s@0.2"
    ],
    "call": [
      "JJ@0.55",
      "TT@0.85",
      "99",
      "88",
      "77",
      "66",
      "55",
      "44",
      "33",
      "22",
      "AQs@0.5",
      "AJs@0.8",
      "ATs",
      "A9s",
      "A8s",
      "A7s",
      "A6s",
      "A5s@0.45",
      "A4s@0.5",
      "A3s@0.55",
      "A2s@0.65",
      "AQo@0.6",
      "AJo@0.55",
      "ATo@0.4",
      "KQs@0.7",
      "KJs",
      "KTs",
      "K9s",
      "K8s@0.7",
      "K7s@0.35",
      "KQo@0.55",
      "KJo@0.3",
      "QJs",
      "QTs",
      "Q9s",
      "Q8s@0.5",
      "JTs",
      "J9s",
      "J8s@0.55",
      "T9s",
      "T8s@0.75",
      "98s",
      "97s@0.6",
      "87s",
      "86s@0.5",
      "76s@0.65",
      "75s@0.45",
      "65s@0.6",
      "64s@0.35",
      "54s@0.55"
    ]
  }
}
